[
  {
    "name": "",
    "txt": ["여느 날과 다름 없이, 같은 시간에, 같은 업무를, 같은 자리에서 시작하였다.\n가축들이 있는 축산 공장에서, 로봇들의 오류 등의 문제 상황을 감시하는 일이다."],
    "type": "event",
    "image": "EventBlack",
    "comment": "검은색 배경 이미지로 대사만 나오게 됩니다."
  },
  {
    "name": "나",
    "txt": ["아침부터 시체를 봤더니 메스꺼운 기분도 조금 들었지만,\n그러한 느낌도 일을 하다보니 곧 사라졌다."]
  },
  {
    "name": "나",
    "txt": ["그렇게 평소와 같던 업무가 이어지던 도중,\n어느 돼지가 크게 울어대는 소리가 내 귀를 찔렀다."]
  },
  {
    "name": "나",
    "txt": ["'뭐 때문에 저리도 울어대는 거지?'"]
  },
  {
    "name": "나",
    "txt": ["나는 유리 너머를 통해 공장 안 쪽, 돼지가 우는 곳을 바라보았다.","어느 돼지가 사육 구역에서 도축 구역으로 옮겨지고 있었고,\n다른 돼지와 서로 마주보며 울어대고 있었다."],
    "image": "Awakeillust"
  },
  {
    "name": "나",
    "txt": ["이내 패널을 통해 알아보니 두 돼지는 어미와 새끼였고,\n어미가 옮겨지고 있는 도중이였던 것이다."]
  },
  {
    "name": "나",
    "txt": ["'그런데 끌려가는 어미 돼지는 그렇다고 쳐도, 왜 새끼까지 우는 거지?,\n부모 개체가 자식 개체를 보호하려 드는 건 종족 보존을 위한 행위라고 해도...'"]
  },
  {
    "name": "나",
    "txt": ["궁금해졌다, '왜 본인이 아닌 남의 고통에 저리 울어대는 것일까?\n뭐가 저 돼지를 그렇게 만든 걸까?' 라는 생각이 머리를 떠나지 않았다."]
  }
] 